Metadata-Version: 2.1
Name: TOPSIS-Priyanka-101803006
Version: 1.0.0
Summary: A Python package implementing TOPSIS technique.
Home-page: https://github.com/gpriya32/TOPSIS-PriyankaGupta-101803006/
Author: Priyanka Gupta
Author-email: priyaagupta55@gmail.com
License: MIT
Download-URL: https://github.com/gpriya32/TOPSIS-PriyankaGupta-101803006/archive/1.0.0.tar.gz
Platform: UNKNOWN
Classifier: License :: OSI Approved :: MIT License
Classifier: Programming Language :: Python :: 3
Classifier: Programming Language :: Python :: 3.4
Classifier: Programming Language :: Python :: 3.5
Classifier: Programming Language :: Python :: 3.6
Classifier: Programming Language :: Python :: 3.7
